setup.py
alkanet_picard.egg-info/PKG-INFO
alkanet_picard.egg-info/SOURCES.txt
alkanet_picard.egg-info/dependency_links.txt
alkanet_picard.egg-info/not-zip-safe
alkanet_picard.egg-info/requires.txt
alkanet_picard.egg-info/top_level.txt
picard/__init__.py
picard/build_model.py
picard/minimizer.py
picard/parse_hypermodel.py
picard/spark_minimizer.py
picard/spaces/__init__.py
picard/spaces/mlp.py
picard/util/__init__.py
picard/util/data_space.py
picard/util/s3.py