Metadata-Version: 1.0
Name: alkanet-picard
Version: 0.1.1
Summary: Declarative Hyperparameter Optimization for Keras models
Home-page: http://github.com/jakebian/picard
Author: Jake Bian
Author-email: jake@getalkanet.com
License: UNKNOWN
Platform: UNKNOWN
